{"id":"170cfd00-edd1-4d90-be4f-6982361240ce","article_link":"https://twitter.com/MPowelly02/status/1790082132389539962","website_source":"Twitter","article_type":"Tweet","summary":null,"title":"Tweet from POWELLY\n@MPowelly02","detailed_content":"#SaitaChain Community \n\nThanks Jimie \n@Your_NLP_Coach\n for Continued Support from you and \n@TheBirbNest\n Team \n\nAlways Supporting  #SaitaChain Blockchain and Native Coin #STC #SaitaChainCoin \n\nI Appreciate it as a Investor","creation_date":"2024-05-13","tags":["#SaitaChain","#SaitaChain","#STC","#SaitaChainCoin","#SaitaChain","#Crypto","#Bridge","#Blockchain","#SaitaChain","#STC","#STC","#SaitaChain","#DeFi","#Crypto","#Invest","#STC","#Vote4SaitaChain"],"author":"POWELLY\n@MPowelly02","category":null}