{"id":"72cb8ec3-5c4a-47fb-a0f9-11d62e3e1373","article_link":"https://twitter.com/BeanFlickersNFT/status/1790113879646740839","website_source":"Twitter","article_type":"Tweet","summary":null,"title":"Tweet from Bean Flickers (Official)\n@BeanFlickersNFT","detailed_content":"Show em if you got em!\n\n#WAGMI $WELL $BASE $ETH #ETH $BTC #BTC $SOL $BLOCK $PARAM $PEPE #Eurovision2024 #Aja $PORK #aespa #Jaemin $POPCAT $TON #XTER #Pepecoin $KITTY $GME #SUGA #DiamonHands #Eric #Polygon #Opensea $BEYOND #BTS #JIMIN #NFT $MATIC $TRIP #Solana #blockchain $ENA","creation_date":"2024-05-13","tags":["#WAGMI","#ETH","#BTC","#Eurovision2024","#Aja","#aespa","#Jaemin","#XTER","#Pepecoin","#SUGA","#DiamonHands","#Eric","#Polygon","#Opensea","#BTS","#JIMIN","#NFT","#Solana","#blockchain"],"author":"Bean Flickers (Official)\n@BeanFlickersNFT","category":null}