{"id":"c01b28e4-631b-4952-93c6-1a5ae8608e5a","article_link":"https://twitter.com/kennycormic/status/1790091290392105307","website_source":"Twitter","article_type":"Tweet","summary":null,"title":"Tweet from kennycormic.nft $YAKU @ricyoffic\n@kennycormic","detailed_content":"Dive into the Yakuverse! \n@YakuCorp\n NFT project\nis reshaping gaming with a play-to-earn metaverse\nstrategy. #YakuCorp #NFT #Metaverse #PlayToEarn\n\nBuilt on the Solana blockchain, the Yakuverse offers\na cyberpunk world where players can earn $YAKU\nby racing motorcycles &","creation_date":"2024-05-13","tags":["#YakuCorp","#NFT","#Metaverse","#PlayToEarn","#BlockchainGaming","#NFTCommunity","#GamingEconomy"],"author":"kennycormic.nft $YAKU @ricyoffic\n@kennycormic","category":null}