{"id":"e6551ff8-d6f7-49dd-b195-63e6cfd32f23","article_link":"https://medium.com/coinmonks/how-to-mint-nfts-programmatically-9dd23c3b5741","website_source":"Medium","article_type":"Blog Post","summary":"In this article, you’ll learn about how you can mint NFTs programmatically using Alchemy and Pinata with 0 Solidity knowledge.","title":"How to mint NFTs programmatically","detailed_content":"Did you know that the NFT industry generated around $24.7 billion in sales last year(Source)? If you’re a programmer trying to get your hands dirty in this space with little or no Blockchain development experience, this article can be a great start for you. In this article, you’ll learn about how you can mint NFTs programmatically using Alchemy and Pinata Cloud with 0 Solidity knowledge. There are 2 parts to this article:","creation_date":"2023-05-02","tags":[],"author":"Aaliya Ali","category":null}